validx/__init__.py
validx/decorators.py
validx/exceptions.py
validx/utils.py
validx/validators.py
validify_py-0.1.0.dist-info/LICENSE
validify_py-0.1.0.dist-info/METADATA
validify_py-0.1.0.dist-info/WHEEL
validify_py-0.1.0.dist-info/top_level.txt
validify_py-0.1.0.dist-info/RECORD
