Metadata-Version: 2.1
Name: validify-py
Version: 0.1.0
Summary: A flexible and extensible validation library for Python
Author: ValidX Contributors
Project-URL: Homepage, https://github.com/2024si96524-Mithun/ValidX
Project-URL: Documentation, https://github.com/2024si96524-Mithun/ValidX#readme
Project-URL: Repository, https://github.com/2024si96524-Mithun/ValidX
Project-URL: Bug Tracker, https://github.com/2024si96524-Mithun/ValidX/issues
Keywords: validation,validator,data-validation,schema-validation
Classifier: Development Status :: 3 - Alpha
Classifier: Intended Audience :: Developers
Classifier: License :: OSI Approved :: MIT License
Classifier: Programming Language :: Python :: 3
Classifier: Programming Language :: Python :: 3.9
Classifier: Programming Language :: Python :: 3.10
Classifier: Programming Language :: Python :: 3.11
Classifier: Programming Language :: Python :: 3.12
Classifier: Programming Language :: Python :: 3.13
Classifier: Topic :: Software Development :: Libraries :: Python Modules
Requires-Python: >=3.9
License-File: LICENSE
Provides-Extra: dev
Requires-Dist: pytest>=7.0.0; extra == "dev"
Requires-Dist: pytest-cov>=4.0.0; extra == "dev"
Requires-Dist: black<25.0.0,>=24.0.0; extra == "dev"
Requires-Dist: flake8>=6.0.0; extra == "dev"
Requires-Dist: mypy>=1.0.0; extra == "dev"
Requires-Dist: isort>=5.12.0; extra == "dev"
